 <lugares>
    <monumento>tumbas antropomórficas</monumento>
    <coordenadas>
      <latitud>39.218308</latitud>
      <longitud>-7.002342</longitud>
    </coordenadas>
  </lugares>
  <lugares>
    <monumento>paseo de la alameda</monumento>
    <coordenadas>
      <latitud>39.219249</latitud>
      <longitud>-7.000578</longitud>
    </coordenadas>
  </lugares>
  <lugares>
    <monumento>paseo de las laderas</monumento>
    <coordenadas>
      <latitud>39.21667</latitud>
      <longitud>-7.003125</longitud>
    </coordenadas>
  </lugares>
  <lugares>
    <monumento>iglesia san mateo</monumento>
    <coordenadas>
      <latitud>39.218215</latitud>
      <longitud>-6.999927</longitud>
    </coordenadas>
  </lugares>
  <lugares>
    <monumento>fuente del caño</monumento>
    <coordenadas>
      <latitud>39.212153</latitud>
      <longitud>-6.996622</longitud>
    </coordenadas>
  </lugares>
  <lugares>
    <monumento>iglesia santa maría del mercado</monumento>
    <coordenadas>
      <latitud>39.218255</latitud>
      <longitud>-7.000762</longitud>
    </coordenadas>
  </lugares>
  <lugares>
    <monumento>iglesia de san francisco</monumento>
    <coordenadas>
      <latitud>39.223106</latitud>
      <longitud>-7.000762</longitud>
    </coordenadas>
  </lugares>
  <lugares>
    <monumento>santuario de carrión</monumento>
    <coordenadas>
      <latitud>39.180424</latitud>
      <longitud>-7.034845</longitud>
    </coordenadas>
  </lugares>
  <lugares>
    <monumento>piedra del berrocal</monumento>
    <coordenadas>
      <latitud>39.218028</latitud>
      <longitud>-6.99826</longitud>
    </coordenadas>
  </lugares>
  <lugares>
    <monumento>plaza de españa</monumento>
    <coordenadas>
      <latitud>39.218744</latitud>
      <longitud>-6.999635</longitud>
    </coordenadas>
  </lugares>
  <lugares>
    <monumento>pinturas rupestres</monumento>
    <coordenadas>
      <latitud>39.221776</latitud>
      <longitud>-7.016119</longitud>
    </coordenadas>
  </lugares>
  <lugares>
    <monumento>castillo de luna</monumento>
    <coordenadas>
      <latitud>39.217425</latitud>
      <longitud>-7.002289</longitud>
    </coordenadas>
  </lugares>
  <lugares>
    <monumento>puerta de valencia</monumento>
    <coordenadas>
      <latitud>39.21895</latitud>
      <longitud>-7.003886</longitud>
    </coordenadas>
  </lugares>
  <lugares>
    <monumento>torre de bacas</monumento>
    <coordenadas>
      <latitud>39.218023</latitud>
      <longitud>-7.001837</longitud>
    </coordenadas>
  </lugares>
  <lugares>
    <monumento>torre del reloj</monumento>
    <coordenadas>
      <latitud>39.218631</latitud>
      <longitud>-7.000155</longitud>
    </coordenadas>
  </lugares>
  <lugares>
    <monumento>puerta de la villa</monumento>
    <coordenadas>
      <latitud>39.218244</latitud>
      <longitud>-7.000253</longitud>
    </coordenadas>
  </lugares>